r4u/__init__.py
r4u/client.py
r4u/utils.py
r4u/tracing/__init__.py
r4u/tracing/http/__init__.py
r4u/tracing/http/aiohttp.py
r4u/tracing/http/auto.py
r4u/tracing/http/httpx.py
r4u/tracing/http/requests.py
r4u-0.1.1.dist-info/METADATA
r4u-0.1.1.dist-info/WHEEL
r4u-0.1.1.dist-info/RECORD
