Metadata-Version: 2.4
Name: r4u
Version: 0.1.1
Summary: Observability SDK for LLM applications
Author: R4U Team
License: Apache 2.0
Requires-Python: >=3.10
Requires-Dist: httpx>=0.28.1
Requires-Dist: pydantic>=2.12.2
Provides-Extra: aiohttp
Requires-Dist: aiohttp>=3.8.0; extra == 'aiohttp'
Provides-Extra: requests
Requires-Dist: requests>=2.25.0; extra == 'requests'
